sctoolsgw/__init__.py
sctoolsgw/sctoolsgw.py
sctoolsgw-0.0.4.dist-info/LICENSE
sctoolsgw-0.0.4.dist-info/METADATA
sctoolsgw-0.0.4.dist-info/WHEEL
sctoolsgw-0.0.4.dist-info/top_level.txt
sctoolsgw-0.0.4.dist-info/RECORD
